pynotionclient/__init__.py
pynotionclient/block.py
pynotionclient/comment.py
pynotionclient/config/__init__.py
pynotionclient/config/constants.py
pynotionclient/config/urls.py
pynotionclient/database.py
pynotionclient/exceptions/__init__.py
pynotionclient/exceptions/pynotion_exceptions.py
pynotionclient/page.py
pynotionclient/py_notion.py
pynotionclient/schema/__init__.py
pynotionclient/schema/common/__init__.py
pynotionclient/schema/common/header_schema.py
pynotionclient/schema/database/__init__.py
pynotionclient/schema/database/annotations_schema_config.py
pynotionclient/schema/database/equation_schema_config.py
pynotionclient/schema/database/mention_schema_config.py
pynotionclient/schema/database/request/__init__.py
pynotionclient/schema/database/request/common_property_configurations.py
pynotionclient/schema/database/request/content_configuration.py
pynotionclient/schema/database/request/database_property_configuration.py
pynotionclient/schema/database/request/number_configuration.py
pynotionclient/schema/database/request/relation_configuration.py
pynotionclient/schema/database/request/select_configuration.py
pynotionclient/schema/database/response/__init__.py
pynotionclient/schema/database/response/check_box_schema.py
pynotionclient/schema/database/response/common_filter_schema.py
pynotionclient/schema/database/response/common_info_schema.py
pynotionclient/schema/database/response/content_schema.py
pynotionclient/schema/database/response/create_database_response_schema.py
pynotionclient/schema/database/response/database_response_schema.py
pynotionclient/schema/database/response/date_filter_schema.py
pynotionclient/schema/database/response/date_schema.py
pynotionclient/schema/database/response/filter_request_schema.py
pynotionclient/schema/database/response/multi_select_schema.py
pynotionclient/schema/database/response/number_filter_schema.py
pynotionclient/schema/database/response/number_schema.py
pynotionclient/schema/database/response/other_filters_schema.py
pynotionclient-0.0.9.dist-info/LICENSE
pynotionclient-0.0.9.dist-info/WHEEL
pynotionclient-0.0.9.dist-info/METADATA
pynotionclient-0.0.9.dist-info/RECORD
