Metadata-Version: 2.1
Name: pynotionclient
Version: 0.0.9
Summary: Python wrapper for Notion API
Home-page: https://github.com/pythonhubpy/PyNotion
License: MIT
Keywords: notion,api,wrapper
Author: Vetrichelvan
Author-email: pythonhub.py@gmail.com
Requires-Python: >=3.8,<4.0
Classifier: License :: OSI Approved :: MIT License
Classifier: Operating System :: OS Independent
Classifier: Programming Language :: Python :: 3
Classifier: Programming Language :: Python :: 3.10
Classifier: Programming Language :: Python :: 3.8
Classifier: Programming Language :: Python :: 3.9
Requires-Dist: pydantic (>=1.10.2,<2.0.0)
Requires-Dist: requests (>=2.28.1,<3.0.0)
Project-URL: Bug Tracker, https://github.com/pythonhubpy/PyNotion/issues
Project-URL: Repository, https://github.com/pythonhubpy/PyNotion
